[
  {
    "category": "Office",
    "correct_answer": "Printer",
    "options": ["Printer", "Scanner", "Mouse", "Keyboard"],
    "photoUrl": "https://images.unsplash.com/photo-1612815154858-60aa4c59eaa6?w=700&auto=format&fit=crop&q=60&ixlib=rb-4.1.0&ixid=M3wxMjA3fDB8MHxzZWFyY2h8Mnx8UHJpbnRlcnxlbnwwfHwwfHx8MA%3D%3D"
  },
  {
    "category": "Office",
    "correct_answer": "Stapler",
    "options": ["Paper clip", "Stapler", "Marker", "Scissors"],
    "photoUrl": "https://images.unsplash.com/photo-1603234408844-15d80c40d580?w=1000&auto=format&fit=crop&q=60&ixlib=rb-4.1.0&ixid=M3wxMjA3fDB8MHxzZWFyY2h8M3x8U3RhcGxlcnxlbnwwfHwwfHx8MA%3D%3D"
  },
  {
    "category": "Office",
    "correct_answer": "Desk",
    "options": ["Desk", "Swivel chair", "Filing cabinet", "Wall calendar"],
    "photoUrl": "https://plus.unsplash.com/premium_photo-1685136482295-4e6209bfdd02?w=1000&auto=format&fit=crop&q=60&ixlib=rb-4.1.0&ixid=M3wxMjA3fDB8MHxzZWFyY2h8NXx8RGVza3xlbnwwfHwwfHx8MA%3D%3D"
  },
  {
    "category": "Office",
    "correct_answer": "Monitor",
    "options": ["Mouse", "Monitor", "Keyboard", "USB"],
    "photoUrl": "https://plus.unsplash.com/premium_photo-1680721575441-18d5a0567269?w=1000&auto=format&fit=crop&q=60&ixlib=rb-4.1.0&ixid=M3wxMjA3fDB8MHxzZWFyY2h8NXx8TW9uaXRvcnxlbnwwfHwwfHx8MA%3D%3D"
  },
  {
    "category": "Office",
    "correct_answer": "Folder",
    "options": ["Ballpoint pen", "Folder", "Printer", "Shredder"],
    "photoUrl": "https://plus.unsplash.com/premium_photo-1677402408071-232d1c3c3787?w=1000&auto=format&fit=crop&q=60&ixlib=rb-4.1.0&ixid=M3wxMjA3fDB8MHxzZWFyY2h8MXx8Rm9sZGVyfGVufDB8fDB8fHww"
  },
  {
    "category": "Office",
    "correct_answer": "Keyboard",
    "options": ["Computer", "Monitor", "Keyboard", "Mouse"],
    "photoUrl": "https://images.unsplash.com/photo-1587829741301-dc798b83add3?w=1000&auto=format&fit=crop&q=60&ixlib=rb-4.1.0&ixid=M3wxMjA3fDB8MHxzZWFyY2h8Mnx8S2V5Ym9hcmR8ZW58MHx8MHx8fDA%3D"
  },
  {
    "category": "Office",
    "correct_answer": "Whiteboard",
    "options": ["Whiteboard", "Sticky notes", "File cabinet", "Scanner"],
    "photoUrl": "https://plus.unsplash.com/premium_photo-1681671796265-4e8925f49df2?w=1000&auto=format&fit=crop&q=60&ixlib=rb-4.1.0&ixid=M3wxMjA3fDB8MHxzZWFyY2h8MXx8V2hpdGVib2FyZHxlbnwwfHwwfHx8MA%3D%3D"
  },
  {
    "category": "Office",
    "correct_answer": "Pen",
    "options": ["Pencil", "Pen", "Scissors", "Ruler"],
    "photoUrl": "https://images.unsplash.com/photo-1583485088034-697b5bc54ccd?w=1000&auto=format&fit=crop&q=60&ixlib=rb-4.1.0&ixid=M3wxMjA3fDB8MHxzZWFyY2h8NHx8UGVufGVufDB8fDB8fHww"
  },
  {
    "category": "Office",
    "correct_answer": "Notepad",
    "options": ["Correction pen", "Notepad", "Printing paper", "Projector"],
    "photoUrl": "https://images.unsplash.com/photo-1612367980327-7454a7276aa7?w=1000&auto=format&fit=crop&q=60&ixlib=rb-4.1.0&ixid=M3wxMjA3fDB8MHxzZWFyY2h8Mnx8Tm90ZXBhZHxlbnwwfHwwfHx8MA%3D%3D"
  },
  {
    "category": "Office",
    "correct_answer": "Shredder",
    "options": ["Shredder", "Printer", "Computer", "Scanner"],
    "photoUrl": "https://images.unsplash.com/photo-1615309662685-397ae100cb15?w=1000&auto=format&fit=crop&q=60&ixlib=rb-4.1.0&ixid=M3wxMjA3fDB8MHxzZWFyY2h8Mnx8U2hyZWRkZXJ8ZW58MHx8MHx8fDA%3D"
  },
  {
    "category": "Food",
    "correct_answer": "Bread",
    "options": ["Meat", "Bread", "Egg", "Rice"],
    "photoUrl": "https://images.unsplash.com/photo-1533782654613-826a072dd6f3?w=1000&auto=format&fit=crop&q=60&ixlib=rb-4.1.0&ixid=M3wxMjA3fDB8MHxzZWFyY2h8M3x8QnJlYWR8ZW58MHx8MHx8fDA%3D"
  },
  {
    "category": "Food",
    "correct_answer": "Apple",
    "options": ["Apple", "Pear", "Watermelon", "Banana"],
    "photoUrl": "https://plus.unsplash.com/premium_photo-1724249990837-f6dfcb7f3eaa?w=1000&auto=format&fit=crop&q=60&ixlib=rb-4.1.0&ixid=M3wxMjA3fDB8MHxzZWFyY2h8MXx8QXBwbGV8ZW58MHx8MHx8fDA%3D"
  },
  {
    "category": "Food",
    "correct_answer": "Carrot",
    "options": ["Cabbage", "Carrot", "Potato", "Bell pepper"],
    "photoUrl": "https://images.unsplash.com/photo-1598170845058-32b9d6a5da37?w=1000&auto=format&fit=crop&q=60&ixlib=rb-4.1.0&ixid=M3wxMjA3fDB8MHxzZWFyY2h8Mnx8Q2Fycm90fGVufDB8fDB8fHww"
  },
  {
    "category": "Food",
    "correct_answer": "Egg",
    "options": ["Egg", "Milk", "Cake", "Noodle"],
    "photoUrl": "https://plus.unsplash.com/premium_photo-1671022581636-e711d888af04?w=1000&auto=format&fit=crop&q=60&ixlib=rb-4.1.0&ixid=M3wxMjA3fDB8MHxzZWFyY2h8MXx8RWdnfGVufDB8fDB8fHww"
  },
  {
    "category": "Food",
    "correct_answer": "Cheese",
    "options": ["Cheese", "Cream", "Soup", "Yogurt"],
    "photoUrl": "https://images.unsplash.com/photo-1683314573422-649a3c6ad784?w=1000&auto=format&fit=crop&q=60&ixlib=rb-4.1.0&ixid=M3wxMjA3fDB8MHxzZWFyY2h8M3x8Q2hlZXNlfGVufDB8fDB8fHww"
  },
  {
    "category": "Food",
    "correct_answer": "Fish",
    "options": ["Chicken", "Beef", "Fish", "Shrimp"],
    "photoUrl": "https://images.unsplash.com/photo-1535591273668-578e31182c4f?w=1000&auto=format&fit=crop&q=60&ixlib=rb-4.1.0&ixid=M3wxMjA3fDB8MHxzZWFyY2h8M3x8RmlzaHxlbnwwfHwwfHx8MA%3D%3D"
  },
  {
    "category": "Food",
    "correct_answer": "Rice",
    "options": ["Pho", "Noodle", "Vermicelli", "Rice"],
    "photoUrl": "https://images.unsplash.com/photo-1586201375761-83865001e31c?w=1000&auto=format&fit=crop&q=60&ixlib=rb-4.1.0&ixid=M3wxMjA3fDB8MHxzZWFyY2h8NHx8UmljZXxlbnwwfHwwfHx8MA%3D%3D"
  },
  {
    "category": "Food",
    "correct_answer": "Banana",
    "options": ["Watermelon", "Banana", "Apple", "Grape"],
    "photoUrl": "https://images.unsplash.com/photo-1481349518771-20055b2a7b24?w=1000&auto=format&fit=crop&q=60&ixlib=rb-4.1.0&ixid=M3wxMjA3fDB8MHxzZWFyY2h8M3x8QmFuYW5hfGVufDB8fDB8fHww"
  },
  {
    "category": "Food",
    "correct_answer": "Chicken",
    "options": ["Fish", "Shrimp", "Chicken", "Pork"],
    "photoUrl": "https://images.unsplash.com/photo-1587593810167-a84920ea0781?w=1000&auto=format&fit=crop&q=60&ixlib=rb-4.1.0&ixid=M3wxMjA3fDB8MHxzZWFyY2h8MTB8fENoaWNrZW58ZW58MHx8MHx8fDA%3D"
  },
  {
    "category": "Food",
    "correct_answer": "Soup",
    "options": ["Rice", "Soup", "Vermicelli", "Sweet soup"],
    "photoUrl": "https://images.unsplash.com/photo-1652088079703-38f4a8d6b981?w=1000&auto=format&fit=crop&q=60&ixlib=rb-4.1.0&ixid=M3wxMjA3fDB8MHxzZWFyY2h8OHx8U291cHxlbnwwfHwwfHx8MA%3D%3D"
  }
]